Workbook

Sheet Assumptions
A1: Metric | B1: Value | C1: Description
A2: Starting Customers | B2: 500 | C2: Current active users
A3: Monthly Growth Rate (Year 1) | B3: 0.2 | C3: 20% MoM Growth
A4: Monthly Growth Rate (Year 2) | B4: 0.15 | C4: 15% MoM Growth
A5: Monthly Growth Rate (Year 3) | B5: 0.1 | C5: 10% MoM Growth
A6: Churn Rate | B6: 0.05 | C6: Monthly Churn
A7: ARPU (Average Rev Per User) | B7: 29 | C7: Weighted Avg Price
A8: CAC | B8: 150 | C8: Cost per Acq
A9: Gross Margin | B9: 0.85 | C9: SaaS Margin
A10: Fixed Costs (Monthly) | B10: 50000 | C10: Salaries, Rent, Server

Sheet Monthly Model
A1: Metric | B1: Month 1 | C1: Month 2 | D1: Month 3 | E1: Month 4 | F1: Month 5 | G1: Month 6 | H1: Month 7 | I1: Month 8 | J1: Month 9 | K1: Month 10 | L1: Month 11 | M1: Month 12 | N1: Month 13 | O1: Month 14 | P1: Month 15 | Q1: Month 16 | R1: Month 17 | S1: Month 18 | T1: Month 19 | U1: Month 20 | V1: Month 21 | W1: Month 22 | X1: Month 23 | Y1: Month 24 | Z1: Month 25 | AA1: Month 26 | AB1: Month 27 | AC1: Month 28 | AD1: Month 29 | AE1: Month 30 | AF1: Month 31 | AG1: Month 32 | AH1: Month 33 | AI1: Month 34 | AJ1: Month 35 | AK1: Month 36
A2: Total Customers | B2: =Assumptions!B2 | C2: =B2+C3-C4 | D2: =C2+D3-D4 | E2: =D2+E3-E4 | F2: =E2+F3-F4 | G2: =F2+G3-G4 | H2: =G2+H3-H4 | I2: =H2+I3-I4 | J2: =I2+J3-J4 | ... AK2: =AJ2+AK3-AK4
A3: New Customers | C3: =B2*Assumptions!B3 | D3: =C2*Assumptions!B3 | E3: =D2*Assumptions!B3 | F3: =E2*Assumptions!B3 | G3: =F2*Assumptions!B3 | H3: =G2*Assumptions!B3 | I3: =H2*Assumptions!B3 | J3: =I2*Assumptions!B3 | K3: =J2*Assumptions!B3 | L3: =K2*Assumptions!B3 | M3: =L2*Assumptions!B3 | N3: =M2*Assumptions!B4 | O3: =N2*Assumptions!B4 | P3: =O2*Assumptions!B4 | Q3: =P2*Assumptions!B4 | R3: =Q2*Assumptions!B4 | S3: =R2*Assumptions!B4 | T3: =S2*Assumptions!B4 | U3: =T2*Assumptions!B4 | V3: =U2*Assumptions!B4 | W3: =V2*Assumptions!B4 | X3: =W2*Assumptions!B4 | Y3: =X2*Assumptions!B4 | Z3: =Y2*Assumptions!B5 | AA3: =Z2*Assumptions!B5 | AB3: =AA2*Assumptions!B5 | AC3: =AB2*Assumptions!B5 | AD3: =AC2*Assumptions!B5 | AE3: =AD2*Assumptions!B5 | AF3: =AE2*Assumptions!B5 | AG3: =AF2*Assumptions!B5 | AH3: =AG2*Assumptions!B5 | AI3: =AH2*Assumptions!B5 | AJ3: =AI2*Assumptions!B5 | AK3: =AJ2*Assumptions!B5
A4: Churned Customers | C4: =B2*Assumptions!B6 | D4: =C2*Assumptions!B6 | E4: =D2*Assumptions!B6 | F4: =E2*Assumptions!B6 | G4: =F2*Assumptions!B6 | H4: =G2*Assumptions!B6 | I4: =H2*Assumptions!B6 | J4: =I2*Assumptions!B6 | K4: =J2*Assumptions!B6 | L4: =K2*Assumptions!B6 | M4: =L2*Assumptions!B6 | N4: =M2*Assumptions!B6 | O4: =N2*Assumptions!B6 | P4: =O2*Assumptions!B6 | Q4: =P2*Assumptions!B6 | R4: =Q2*Assumptions!B6 | S4: =R2*Assumptions!B6 | T4: =S2*Assumptions!B6 | U4: =T2*Assumptions!B6 | V4: =U2*Assumptions!B6 | W4: =V2*Assumptions!B6 | X4: =W2*Assumptions!B6 | Y4: =X2*Assumptions!B6 | Z4: =Y2*Assumptions!B6 | AA4: =Z2*Assumptions!B6 | AB4: =AA2*Assumptions!B6 | AC4: =AB2*Assumptions!B6 | AD4: =AC2*Assumptions!B6 | AE4: =AD2*Assumptions!B6 | AF4: =AE2*Assumptions!B6 | AG4: =AF2*Assumptions!B6 | AH4: =AG2*Assumptions!B6 | AI4: =AH2*Assumptions!B6 | AJ4: =AI2*Assumptions!B6 | AK4: =AJ2*Assumptions!B6
A5: Revenue (MRR) | B5: =B2*Assumptions!B7 | C5: =C2*Assumptions!B7 | D5: =D2*Assumptions!B7 | E5: =E2*Assumptions!B7 | F5: =F2*Assumptions!B7 | G5: =G2*Assumptions!B7 | H5: =H2*Assumptions!B7 | I5: =I2*Assumptions!B7 | J5: =J2*Assumptions!B7 | K5: =K2*Assumptions!B7 | L5: =L2*Assumptions!B7 | M5: =M2*Assumptions!B7 | N5: =N2*Assumptions!B7 | O5: =O2*Assumptions!B7 | P5: =P2*Assumptions!B7 | Q5: =Q2*Assumptions!B7 | R5: =R2*Assumptions!B7 | S5: =S2*Assumptions!B7 | T5: =T2*Assumptions!B7 | U5: =U2*Assumptions!B7 | V5: =V2*Assumptions!B7 | W5: =W2*Assumptions!B7 | X5: =X2*Assumptions!B7 | Y5: =Y2*Assumptions!B7 | Z5: =Z2*Assumptions!B7 | AA5: =AA2*Assumptions!B7 | AB5: =AB2*Assumptions!B7 | AC5: =AC2*Assumptions!B7 | AD5: =AD2*Assumptions!B7 | AE5: =AE2*Assumptions!B7 | AF5: =AF2*Assumptions!B7 | AG5: =AG2*Assumptions!B7 | AH5: =AH2*Assumptions!B7 | AI5: =AI2*Assumptions!B7 | AJ5: =AJ2*Assumptions!B7 | AK5: =AK2*Assumptions!B7
A6: COGS | B6: =B5*(1-Assumptions!B9) | C6: =C5*(1-Assumptions!B9) | D6: =D5*(1-Assumptions!B9) | E6: =E5*(1-Assumptions!B9) | F6: =F5*(1-Assumptions!B9) | G6: =G5*(1-Assumptions!B9) | H6: =H5*(1-Assumptions!B9) | I6: =I5*(1-Assumptions!B9) | J6: =J5*(1-Assumptions!B9) | K6: =K5*(1-Assumptions!B9) | L6: =L5*(1-Assumptions!B9) | M6: =M5*(1-Assumptions!B9) | N6: =N5*(1-Assumptions!B9) | O6: =O5*(1-Assumptions!B9) | P6: =P5*(1-Assumptions!B9) | Q6: =Q5*(1-Assumptions!B9) | R6: =R5*(1-Assumptions!B9) | S6: =S5*(1-Assumptions!B9) | T6: =T5*(1-Assumptions!B9) | U6: =U5*(1-Assumptions!B9) | V6: =V5*(1-Assumptions!B9) | W6: =W5*(1-Assumptions!B9) | X6: =X5*(1-Assumptions!B9) | Y6: =Y5*(1-Assumptions!B9) | Z6: =Z5*(1-Assumptions!B9) | AA6: =AA5*(1-Assumptions!B9) | AB6: =AB5*(1-Assumptions!B9) | AC6: =AC5*(1-Assumptions!B9) | AD6: =AD5*(1-Assumptions!B9) | AE6: =AE5*(1-Assumptions!B9) | AF6: =AF5*(1-Assumptions!B9) | AG6: =AG5*(1-Assumptions!B9) | AH6: =AH5*(1-Assumptions!B9) | AI6: =AI5*(1-Assumptions!B9) | AJ6: =AJ5*(1-Assumptions!B9) | AK6: =AK5*(1-Assumptions!B9)
A7: Gross Profit | B7: =B5-B6 | C7: =C5-C6 | D7: =D5-D6 | E7: =E5-E6 | F7: =F5-F6 | G7: =G5-G6 | H7: =H5-H6 | I7: =I5-I6 | ... AK7: =AK5-AK6
A8: OpEx | B8: =Assumptions!B10 | C8: =B8*1.02 | D8: =C8*1.02 | E8: =D8*1.02 | F8: =E8*1.02 | G8: =F8*1.02 | H8: =G8*1.02 | I8: =H8*1.02 | J8: =I8*1.02 | ... AK8: =AJ8*1.02
A9: EBITDA | B9: =B7-B8 | C9: =C7-C8 | D9: =D7-D8 | E9: =E7-E8 | F9: =F7-F8 | G9: =G7-G8 | H9: =H7-H8 | I9: =I7-I8 | ... AK9: =AK7-AK8

Sheet Visuals
